<?xml version="1.0" encoding="UTF-8"?>
<config xmlns="http://www.knime.org/2008/09/XMLConfig" xmlns:xsi="http://www.w3.org/2001/XMLSchema-instance" xsi:schemaLocation="http://www.knime.org/2008/09/XMLConfig http://www.knime.org/XMLConfig_2008_09.xsd" key="spec.xml">
    <entry key="spec_name" type="xstring" value="default"/>
    <entry key="number_columns" type="xint" value="11"/>
    <config key="column_spec_0">
        <entry key="column_name" type="xstring" value="ID"/>
        <config key="element_names">
            <entry key="array-size" type="xint" value="0"/>
        </config>
        <config key="column_type">
            <entry key="cell_class" type="xstring" value="org.knime.core.data.def.IntCell"/>
        </config>
        <config key="column_domain">
            <config key="lower_bound">
                <entry key="datacell" type="xstring" value="org.knime.core.data.def.IntCell"/>
                <config key="org.knime.core.data.def.IntCell">
                    <entry key="IntCell" type="xint" value="458982"/>
                </config>
            </config>
            <config key="upper_bound">
                <entry key="datacell" type="xstring" value="org.knime.core.data.def.IntCell"/>
                <config key="org.knime.core.data.def.IntCell">
                    <entry key="IntCell" type="xint" value="467974"/>
                </config>
            </config>
        </config>
        <config key="column_properties"/>
        <config key="meta_data"/>
    </config>
    <config key="column_spec_1">
        <entry key="column_name" type="xstring" value="Gender"/>
        <config key="element_names">
            <entry key="array-size" type="xint" value="0"/>
        </config>
        <config key="column_type">
            <entry key="cell_class" type="xstring" value="org.knime.core.data.def.StringCell"/>
        </config>
        <config key="column_domain">
            <config key="possible_values">
                <entry key="array-size" type="xint" value="2"/>
                <config key="0">
                    <entry key="datacell" type="xstring" value="org.knime.core.data.def.StringCell"/>
                    <config key="org.knime.core.data.def.StringCell">
                        <entry key="StringCell" type="xstring" value="Male"/>
                    </config>
                </config>
                <config key="1">
                    <entry key="datacell" type="xstring" value="org.knime.core.data.def.StringCell"/>
                    <config key="org.knime.core.data.def.StringCell">
                        <entry key="StringCell" type="xstring" value="Female"/>
                    </config>
                </config>
            </config>
        </config>
        <config key="column_properties"/>
        <config key="meta_data"/>
    </config>
    <config key="column_spec_2">
        <entry key="column_name" type="xstring" value="Ever_Married"/>
        <config key="element_names">
            <entry key="array-size" type="xint" value="0"/>
        </config>
        <config key="column_type">
            <entry key="cell_class" type="xstring" value="org.knime.core.data.def.StringCell"/>
        </config>
        <config key="column_domain">
            <config key="possible_values">
                <entry key="array-size" type="xint" value="2"/>
                <config key="0">
                    <entry key="datacell" type="xstring" value="org.knime.core.data.def.StringCell"/>
                    <config key="org.knime.core.data.def.StringCell">
                        <entry key="StringCell" type="xstring" value="No"/>
                    </config>
                </config>
                <config key="1">
                    <entry key="datacell" type="xstring" value="org.knime.core.data.def.StringCell"/>
                    <config key="org.knime.core.data.def.StringCell">
                        <entry key="StringCell" type="xstring" value="Yes"/>
                    </config>
                </config>
            </config>
        </config>
        <config key="column_properties"/>
        <config key="meta_data"/>
    </config>
    <config key="column_spec_3">
        <entry key="column_name" type="xstring" value="Age"/>
        <config key="element_names">
            <entry key="array-size" type="xint" value="0"/>
        </config>
        <config key="column_type">
            <entry key="cell_class" type="xstring" value="org.knime.core.data.def.IntCell"/>
        </config>
        <config key="column_domain">
            <config key="lower_bound">
                <entry key="datacell" type="xstring" value="org.knime.core.data.def.IntCell"/>
                <config key="org.knime.core.data.def.IntCell">
                    <entry key="IntCell" type="xint" value="18"/>
                </config>
            </config>
            <config key="upper_bound">
                <entry key="datacell" type="xstring" value="org.knime.core.data.def.IntCell"/>
                <config key="org.knime.core.data.def.IntCell">
                    <entry key="IntCell" type="xint" value="89"/>
                </config>
            </config>
        </config>
        <config key="column_properties"/>
        <config key="meta_data"/>
    </config>
    <config key="column_spec_4">
        <entry key="column_name" type="xstring" value="Graduated"/>
        <config key="element_names">
            <entry key="array-size" type="xint" value="0"/>
        </config>
        <config key="column_type">
            <entry key="cell_class" type="xstring" value="org.knime.core.data.def.StringCell"/>
        </config>
        <config key="column_domain">
            <config key="possible_values">
                <entry key="array-size" type="xint" value="2"/>
                <config key="0">
                    <entry key="datacell" type="xstring" value="org.knime.core.data.def.StringCell"/>
                    <config key="org.knime.core.data.def.StringCell">
                        <entry key="StringCell" type="xstring" value="No"/>
                    </config>
                </config>
                <config key="1">
                    <entry key="datacell" type="xstring" value="org.knime.core.data.def.StringCell"/>
                    <config key="org.knime.core.data.def.StringCell">
                        <entry key="StringCell" type="xstring" value="Yes"/>
                    </config>
                </config>
            </config>
        </config>
        <config key="column_properties"/>
        <config key="meta_data"/>
    </config>
    <config key="column_spec_5">
        <entry key="column_name" type="xstring" value="Profession"/>
        <config key="element_names">
            <entry key="array-size" type="xint" value="0"/>
        </config>
        <config key="column_type">
            <entry key="cell_class" type="xstring" value="org.knime.core.data.def.StringCell"/>
        </config>
        <config key="column_domain">
            <config key="possible_values">
                <entry key="array-size" type="xint" value="9"/>
                <config key="0">
                    <entry key="datacell" type="xstring" value="org.knime.core.data.def.StringCell"/>
                    <config key="org.knime.core.data.def.StringCell">
                        <entry key="StringCell" type="xstring" value="Healthcare"/>
                    </config>
                </config>
                <config key="1">
                    <entry key="datacell" type="xstring" value="org.knime.core.data.def.StringCell"/>
                    <config key="org.knime.core.data.def.StringCell">
                        <entry key="StringCell" type="xstring" value="Engineer"/>
                    </config>
                </config>
                <config key="2">
                    <entry key="datacell" type="xstring" value="org.knime.core.data.def.StringCell"/>
                    <config key="org.knime.core.data.def.StringCell">
                        <entry key="StringCell" type="xstring" value="Lawyer"/>
                    </config>
                </config>
                <config key="3">
                    <entry key="datacell" type="xstring" value="org.knime.core.data.def.StringCell"/>
                    <config key="org.knime.core.data.def.StringCell">
                        <entry key="StringCell" type="xstring" value="Entertainment"/>
                    </config>
                </config>
                <config key="4">
                    <entry key="datacell" type="xstring" value="org.knime.core.data.def.StringCell"/>
                    <config key="org.knime.core.data.def.StringCell">
                        <entry key="StringCell" type="xstring" value="Artist"/>
                    </config>
                </config>
                <config key="5">
                    <entry key="datacell" type="xstring" value="org.knime.core.data.def.StringCell"/>
                    <config key="org.knime.core.data.def.StringCell">
                        <entry key="StringCell" type="xstring" value="Executive"/>
                    </config>
                </config>
                <config key="6">
                    <entry key="datacell" type="xstring" value="org.knime.core.data.def.StringCell"/>
                    <config key="org.knime.core.data.def.StringCell">
                        <entry key="StringCell" type="xstring" value="Doctor"/>
                    </config>
                </config>
                <config key="7">
                    <entry key="datacell" type="xstring" value="org.knime.core.data.def.StringCell"/>
                    <config key="org.knime.core.data.def.StringCell">
                        <entry key="StringCell" type="xstring" value="Homemaker"/>
                    </config>
                </config>
                <config key="8">
                    <entry key="datacell" type="xstring" value="org.knime.core.data.def.StringCell"/>
                    <config key="org.knime.core.data.def.StringCell">
                        <entry key="StringCell" type="xstring" value="Marketing"/>
                    </config>
                </config>
            </config>
        </config>
        <config key="column_properties"/>
        <config key="meta_data"/>
    </config>
    <config key="column_spec_6">
        <entry key="column_name" type="xstring" value="Work_Experience"/>
        <config key="element_names">
            <entry key="array-size" type="xint" value="0"/>
        </config>
        <config key="column_type">
            <entry key="cell_class" type="xstring" value="org.knime.core.data.def.IntCell"/>
        </config>
        <config key="column_domain">
            <config key="lower_bound">
                <entry key="datacell" type="xstring" value="org.knime.core.data.def.IntCell"/>
                <config key="org.knime.core.data.def.IntCell">
                    <entry key="IntCell" type="xint" value="0"/>
                </config>
            </config>
            <config key="upper_bound">
                <entry key="datacell" type="xstring" value="org.knime.core.data.def.IntCell"/>
                <config key="org.knime.core.data.def.IntCell">
                    <entry key="IntCell" type="xint" value="14"/>
                </config>
            </config>
        </config>
        <config key="column_properties"/>
        <config key="meta_data"/>
    </config>
    <config key="column_spec_7">
        <entry key="column_name" type="xstring" value="Spending_Score"/>
        <config key="element_names">
            <entry key="array-size" type="xint" value="0"/>
        </config>
        <config key="column_type">
            <entry key="cell_class" type="xstring" value="org.knime.core.data.def.StringCell"/>
        </config>
        <config key="column_domain">
            <config key="possible_values">
                <entry key="array-size" type="xint" value="3"/>
                <config key="0">
                    <entry key="datacell" type="xstring" value="org.knime.core.data.def.StringCell"/>
                    <config key="org.knime.core.data.def.StringCell">
                        <entry key="StringCell" type="xstring" value="Low"/>
                    </config>
                </config>
                <config key="1">
                    <entry key="datacell" type="xstring" value="org.knime.core.data.def.StringCell"/>
                    <config key="org.knime.core.data.def.StringCell">
                        <entry key="StringCell" type="xstring" value="Average"/>
                    </config>
                </config>
                <config key="2">
                    <entry key="datacell" type="xstring" value="org.knime.core.data.def.StringCell"/>
                    <config key="org.knime.core.data.def.StringCell">
                        <entry key="StringCell" type="xstring" value="High"/>
                    </config>
                </config>
            </config>
        </config>
        <config key="column_properties"/>
        <config key="meta_data"/>
    </config>
    <config key="column_spec_8">
        <entry key="column_name" type="xstring" value="Family_Size"/>
        <config key="element_names">
            <entry key="array-size" type="xint" value="0"/>
        </config>
        <config key="column_type">
            <entry key="cell_class" type="xstring" value="org.knime.core.data.def.IntCell"/>
        </config>
        <config key="column_domain">
            <config key="lower_bound">
                <entry key="datacell" type="xstring" value="org.knime.core.data.def.IntCell"/>
                <config key="org.knime.core.data.def.IntCell">
                    <entry key="IntCell" type="xint" value="1"/>
                </config>
            </config>
            <config key="upper_bound">
                <entry key="datacell" type="xstring" value="org.knime.core.data.def.IntCell"/>
                <config key="org.knime.core.data.def.IntCell">
                    <entry key="IntCell" type="xint" value="9"/>
                </config>
            </config>
        </config>
        <config key="column_properties"/>
        <config key="meta_data"/>
    </config>
    <config key="column_spec_9">
        <entry key="column_name" type="xstring" value="Var_1"/>
        <config key="element_names">
            <entry key="array-size" type="xint" value="0"/>
        </config>
        <config key="column_type">
            <entry key="cell_class" type="xstring" value="org.knime.core.data.def.StringCell"/>
        </config>
        <config key="column_domain">
            <config key="possible_values">
                <entry key="array-size" type="xint" value="7"/>
                <config key="0">
                    <entry key="datacell" type="xstring" value="org.knime.core.data.def.StringCell"/>
                    <config key="org.knime.core.data.def.StringCell">
                        <entry key="StringCell" type="xstring" value="Cat_4"/>
                    </config>
                </config>
                <config key="1">
                    <entry key="datacell" type="xstring" value="org.knime.core.data.def.StringCell"/>
                    <config key="org.knime.core.data.def.StringCell">
                        <entry key="StringCell" type="xstring" value="Cat_6"/>
                    </config>
                </config>
                <config key="2">
                    <entry key="datacell" type="xstring" value="org.knime.core.data.def.StringCell"/>
                    <config key="org.knime.core.data.def.StringCell">
                        <entry key="StringCell" type="xstring" value="Cat_7"/>
                    </config>
                </config>
                <config key="3">
                    <entry key="datacell" type="xstring" value="org.knime.core.data.def.StringCell"/>
                    <config key="org.knime.core.data.def.StringCell">
                        <entry key="StringCell" type="xstring" value="Cat_3"/>
                    </config>
                </config>
                <config key="4">
                    <entry key="datacell" type="xstring" value="org.knime.core.data.def.StringCell"/>
                    <config key="org.knime.core.data.def.StringCell">
                        <entry key="StringCell" type="xstring" value="Cat_1"/>
                    </config>
                </config>
                <config key="5">
                    <entry key="datacell" type="xstring" value="org.knime.core.data.def.StringCell"/>
                    <config key="org.knime.core.data.def.StringCell">
                        <entry key="StringCell" type="xstring" value="Cat_2"/>
                    </config>
                </config>
                <config key="6">
                    <entry key="datacell" type="xstring" value="org.knime.core.data.def.StringCell"/>
                    <config key="org.knime.core.data.def.StringCell">
                        <entry key="StringCell" type="xstring" value="Cat_5"/>
                    </config>
                </config>
            </config>
        </config>
        <config key="column_properties"/>
        <config key="meta_data"/>
    </config>
    <config key="column_spec_10">
        <entry key="column_name" type="xstring" value="Segmentation"/>
        <config key="element_names">
            <entry key="array-size" type="xint" value="0"/>
        </config>
        <config key="column_type">
            <entry key="cell_class" type="xstring" value="org.knime.core.data.def.StringCell"/>
        </config>
        <config key="column_domain">
            <config key="possible_values">
                <entry key="array-size" type="xint" value="4"/>
                <config key="0">
                    <entry key="datacell" type="xstring" value="org.knime.core.data.def.StringCell"/>
                    <config key="org.knime.core.data.def.StringCell">
                        <entry key="StringCell" type="xstring" value="D"/>
                    </config>
                </config>
                <config key="1">
                    <entry key="datacell" type="xstring" value="org.knime.core.data.def.StringCell"/>
                    <config key="org.knime.core.data.def.StringCell">
                        <entry key="StringCell" type="xstring" value="A"/>
                    </config>
                </config>
                <config key="2">
                    <entry key="datacell" type="xstring" value="org.knime.core.data.def.StringCell"/>
                    <config key="org.knime.core.data.def.StringCell">
                        <entry key="StringCell" type="xstring" value="B"/>
                    </config>
                </config>
                <config key="3">
                    <entry key="datacell" type="xstring" value="org.knime.core.data.def.StringCell"/>
                    <config key="org.knime.core.data.def.StringCell">
                        <entry key="StringCell" type="xstring" value="C"/>
                    </config>
                </config>
            </config>
        </config>
        <config key="column_properties"/>
        <config key="meta_data"/>
    </config>
</config>
